{
  "context-menu": {
    "atom-text-editor": [
      {
        "label": "Generate component from snippet (fancy-react)",
        "command": "fancy-react:generate"
      },
      {
        "label": "Generate tests for source file (fancy-react)",
        "command": "fancy-react:tests"
      },
      {
        "label": "Switch between source <-> test file (fancy-react)",
        "command": "fancy-react:switch"
      }
    ]
  },
  "menu": [
    {
      "label": "Packages",
      "submenu": [
        {
          "label": "fancy-react",
          "submenu": [
            {
              "label": "Generate component from snippet",
              "command": "fancy-react:generate"
            },
            {
              "label": "Generate tests for source file",
              "command": "fancy-react:tests"
            },
            {
              "label": "Switch between source <-> test file",
              "command": "fancy-react:switch"
            }
          ]
        }
      ]
    }
  ]
}
